tests/__init__.py
tests/test_main.py
torchconvquality/__init__.py
torchconvquality-0.3.0.dist-info/LICENSE
torchconvquality-0.3.0.dist-info/METADATA
torchconvquality-0.3.0.dist-info/WHEEL
torchconvquality-0.3.0.dist-info/top_level.txt
torchconvquality-0.3.0.dist-info/RECORD
