Metadata-Version: 2.1
Name: torchconvquality
Version: 0.3.0
Summary: A library for PyTorch model convolution quality analysis.
Home-page: https://github.com/paulgavrikov/torchconvquality
Author: Paul Gavrikov
Author-email: paul.gavrikov@hs-offenburg.de
Classifier: Programming Language :: Python :: 3
Classifier: License :: OSI Approved :: MIT License
Classifier: Operating System :: OS Independent
Requires-Python: >=3.6
License-File: LICENSE
Requires-Dist: torch
Requires-Dist: numpy
